task3/f1_fsm.sv
module f1_fsm(
    input logic rst,
    input logic en,
    input logic clk,
    output logic [7:0] dout
);

// states
typedef enum  {S0, S1, S2, S3, S4, S5, S6, S7, S8 } states;
states current, next;

// register logic
always_ff @(posedge en, posedge rst) begin
    if (rst) current <= S0;
    else if (en) current <= next;
    else current <= current;
end

// next state logic 
always_comb begin
    case (current)
        S0: next = S1;
        S1: next = S2;
        S2: next = S3;
        S3: next = S4;
        S4: next = S5;
        S5: next = S6;
        S6: next = S7;
        S7: next = S8;
        S8: next = S0;
        default: next = S0;
    endcase
// output logic
    case (current)
        S0: dout = {8'b0};
        S1: dout = {7'b0, 1'b1};
        S2: dout = {6'b0, 2'b11};
        S3: dout = {5'b0, 3'b111};
        S4: dout = {4'b0, 4'b1111};
        S5: dout = {3'b0, 5'b11111};
        S6: dout = {2'b0, 6'b111111};
        S7: dout = {1'b0, 7'b1111111};
        S8: dout = {8'b11111111};
        default: dout = {8'b0};
    endcase
end
endmodule

task4/clktick.sv
module clktick #(
	parameter WIDTH = 16
)(
  // interface signals
  input  logic             clk,      // clock 
  input  logic             rst,      // reset
  input  logic             en,       // enable signal
  input  logic [WIDTH-1:0] N,    	 // clock divided by N+1
  output logic  		       tick      // tick output
);

logic [WIDTH-1:0] count;

always_ff @ (posedge clk)
    if (rst) begin
        tick <= 1'b0;
        count <= N;  
        end
    else if (en) begin
	    if (count == 0) begin
		    tick <= 1'b1;
		    count <= N;
	        end
	    else begin
		    tick <= 1'b0;
		    count <= count - 1'b1;
	        end
        end
endmodule

task3/top.sv
module top
#(
    parameter WIDTH = 16
)
(
    input logic clk,
    input logic en,
    input logic rst,
    input logic [WIDTH-1:0] N,
    output logic tick,
    output logic [7:0] dout
);

clktick myClockTick(
    .clk (clk),
    .rst (rst),
    .en(en),
    .N (N),
    .tick(tick)
);

f1_fsm myF1(
    .clk (clk),
    .rst (rst),
    .en (tick),
    .dout (dout)
);

endmodule

task3/clktick.vcd
$version Generated by VerilatedVcd $end
$date Sat Nov  5 16:59:16 2022 $end
$timescale 1ps $end

 $scope module TOP $end
  $var wire 16 & N [15:0] $end
  $var wire  1 # clk $end
  $var wire  8 ( dout [7:0] $end
  $var wire  1 $ en $end
  $var wire  1 % rst $end
  $var wire  1 ' tick $end
  $scope module top $end
   $var wire 16 & N [15:0] $end
   $var wire 32 , WIDTH [31:0] $end
   $var wire  1 # clk $end
   $var wire  8 ( dout [7:0] $end
   $var wire  1 $ en $end
   $var wire  1 % rst $end
   $var wire  1 ' tick $end
   $scope module myClockTick $end
    $var wire 16 & N [15:0] $end
    $var wire 32 , WIDTH [31:0] $end
    $var wire  1 # clk $end
    $var wire 16 ) count [15:0] $end
    $var wire  1 $ en $end
    $var wire  1 % rst $end
    $var wire  1 ' tick $end
   $upscope $end
   $scope module myF1 $end
    $var wire  1 # clk $end
    $var wire 32 * current [31:0] $end
    $var wire  8 ( dout [7:0] $end
    $var wire  1 ' en $end
    $var wire 32 + next [31:0] $end
    $var wire  1 % rst $end
   $upscope $end
  $upscope $end
 $upscope $end
$enddefinitions $end


#0
1#
0$
0%
b0000000000011001 &
0'
b00000000 (
b0000000000000000 )
b00000000000000000000000000000000 *
b00000000000000000000000000000001 +
b00000000000000000000000000010000 ,
#1
0#
#2
1#
1%
#3
0#
#4
1#
b0000000000011001 )
#5
0#
#6
1#
0%
#7
0#
#8
1#
1$
#9
0#
#10
1#
b0000000000011000 )
#11
0#
#12
1#
b0000000000010111 )
#13
0#
#14
1#
b0000000000010110 )
#15
0#
#16
1#
b0000000000010101 )
#17
0#
#18
1#
b0000000000010100 )
#19
0#
#20
1#
b0000000000010011 )
#21
0#
#22
1#
b0000000000010010 )
#23
0#
#24
1#
b0000000000010001 )
#25
0#
#26
1#
b0000000000010000 )
#27
0#
#28
1#
b0000000000001111 )
#29
0#
#30
1#
b0000000000001110 )
#31
0#
#32
1#
b0000000000001101 )
#33
0#
#34
1#
b0000000000001100 )
#35
0#
#36
1#
b0000000000001011 )
#37
0#
#38
1#
b0000000000001010 )
#39
0#
#40
1#
b0000000000001001 )
#41
0#
#42
1#
b0000000000001000 )
#43
0#
#44
1#
b0000000000000111 )
#45
0#
#46
1#
b0000000000000110 )
#47
0#
#48
1#
b0000000000000101 )
#49
0#
#50
1#
b0000000000000100 )
#51
0#
#52
1#
b0000000000000011 )
#53
0#
#54
1#
b0000000000000010 )
#55
0#
#56
1#
b0000000000000001 )
#57
0#
#58
1#
b0000000000000000 )
#59
0#
#60
1#
1'
b00000001 (
b0000000000011001 )
b00000000000000000000000000000001 *
b00000000000000000000000000000010 +
#61
0#
#62
1#
0'
b0000000000011000 )
#63
0#
#64
1#
b0000000000010111 )
#65
0#
#66
1#
b0000000000010110 )
#67
0#
#68
1#
b0000000000010101 )
#69
0#
#70
1#
b0000000000010100 )
#71
0#
#72
1#
b0000000000010011 )
#73
0#
#74
1#
b0000000000010010 )
#75
0#
#76
1#
b0000000000010001 )
#77
0#
#78
1#
b0000000000010000 )
#79
0#
#80
1#
b0000000000001111 )
#81
0#
#82
1#
b0000000000001110 )
#83
0#
#84
1#
b0000000000001101 )
#85
0#
#86
1#
b0000000000001100 )
#87
0#
#88
1#
b0000000000001011 )
#89
0#
#90
1#
b0000000000001010 )
#91
0#
#92
1#
b0000000000001001 )
#93
0#
#94
1#
b0000000000001000 )
#95
0#
#96
1#
b0000000000000111 )
#97
0#
#98
1#
b0000000000000110 )
#99
0#
#100
1#
b0000000000000101 )
#101
0#
#102
1#
b0000000000000100 )
#103
0#
#104
1#
b0000000000000011 )
#105
0#
#106
1#
b0000000000000010 )
#107
0#
#108
1#
b0000000000000001 )
#109
0#
#110
1#
b0000000000000000 )
#111
0#
#112
1#
1'
b00000011 (
b0000000000011001 )
b00000000000000000000000000000010 *
b00000000000000000000000000000011 +
#113
0#
#114
1#
0'
b0000000000011000 )
#115
0#
#116
1#
b0000000000010111 )
#117
0#
#118
1#
b0000000000010110 )
#119
0#
#120
1#
b0000000000010101 )
#121
0#
#122
1#
b0000000000010100 )
#123
0#
#124
1#
b0000000000010011 )
#125
0#
#126
1#
b0000000000010010 )
#127
0#
#128
1#
b0000000000010001 )
#129
0#
#130
1#
b0000000000010000 )
#131
0#
#132
1#
b0000000000001111 )
#133
0#
#134
1#
b0000000000001110 )
#135
0#
#136
1#
b0000000000001101 )
#137
0#
#138
1#
b0000000000001100 )
#139
0#
#140
1#
b0000000000001011 )
#141
0#
#142
1#
b0000000000001010 )
#143
0#
#144
1#
b0000000000001001 )
#145
0#
#146
1#
b0000000000001000 )
#147
0#
#148
1#
b0000000000000111 )
#149
0#
#150
1#
b0000000000000110 )
#151
0#
#152
1#
b0000000000000101 )
#153
0#
#154
1#
b0000000000000100 )
#155
0#
#156
1#
b0000000000000011 )
#157
0#
#158
1#
b0000000000000010 )
#159
0#
#160
1#
b0000000000000001 )
#161
0#
#162
1#
b0000000000000000 )
#163
0#
#164
1#
1'
b00000111 (
b0000000000011001 )
b00000000000000000000000000000011 *
b00000000000000000000000000000100 +
#165
0#
#166
1#
0'
b0000000000011000 )
#167
0#
#168
1#
b0000000000010111 )
#169
0#
#170
1#
b0000000000010110 )
#171
0#
#172
1#
b0000000000010101 )
#173
0#
#174
1#
b0000000000010100 )
#175
0#
#176
1#
b0000000000010011 )
#177
0#
#178
1#
b0000000000010010 )
#179
0#
#180
1#
b0000000000010001 )
#181
0#
#182
1#
b0000000000010000 )
#183
0#
#184
1#
b0000000000001111 )
#185
0#
#186
1#
b0000000000001110 )
#187
0#
#188
1#
b0000000000001101 )
#189
0#
#190
1#
b0000000000001100 )
#191
0#
#192
1#
b0000000000001011 )
#193
0#
#194
1#
b0000000000001010 )
#195
0#
#196
1#
b0000000000001001 )
#197
0#
#198
1#
b0000000000001000 )
#199
0#
#200
1#
b0000000000000111 )
#201
0#
#202
1#
b0000000000000110 )
#203
0#
#204
1#
b0000000000000101 )
#205
0#
#206
1#
b0000000000000100 )
#207
0#
#208
1#
b0000000000000011 )
#209
0#
#210
1#
b0000000000000010 )
#211
0#
#212
1#
b0000000000000001 )
#213
0#
#214
1#
b0000000000000000 )
#215
0#
#216
1#
1'
b00001111 (
b0000000000011001 )
b00000000000000000000000000000100 *
b00000000000000000000000000000101 +
#217
0#
#218
1#
0'
b0000000000011000 )
#219
0#
#220
1#
b0000000000010111 )
#221
0#
#222
1#
b0000000000010110 )
#223
0#
#224
1#
b0000000000010101 )
#225
0#
#226
1#
b0000000000010100 )
#227
0#
#228
1#
b0000000000010011 )
#229
0#
#230
1#
b0000000000010010 )
#231
0#
#232
1#
b0000000000010001 )
#233
0#
#234
1#
b0000000000010000 )
#235
0#
#236
1#
b0000000000001111 )
#237
0#
#238
1#
b0000000000001110 )
#239
0#
#240
1#
b0000000000001101 )
#241
0#
#242
1#
b0000000000001100 )
#243
0#
#244
1#
b0000000000001011 )
#245
0#
#246
1#
b0000000000001010 )
#247
0#
#248
1#
b0000000000001001 )
#249
0#
#250
1#
b0000000000001000 )
#251
0#
#252
1#
b0000000000000111 )
#253
0#
#254
1#
b0000000000000110 )
#255
0#
#256
1#
b0000000000000101 )
#257
0#
#258
1#
b0000000000000100 )
#259
0#
#260
1#
b0000000000000011 )
#261
0#
#262
1#
b0000000000000010 )
#263
0#
#264
1#
b0000000000000001 )
#265
0#
#266
1#
b0000000000000000 )
#267
0#
#268
1#
1'
b00011111 (
b0000000000011001 )
b00000000000000000000000000000101 *
b00000000000000000000000000000110 +
#269
0#
#270
1#
0'
b0000000000011000 )
#271
0#
#272
1#
b0000000000010111 )
#273
0#
#274
1#
b0000000000010110 )
#275
0#
#276
1#
b0000000000010101 )
#277
0#
#278
1#
b0000000000010100 )
#279
0#
#280
1#
b0000000000010011 )
#281
0#
#282
1#
b0000000000010010 )
#283
0#
#284
1#
b0000000000010001 )
#285
0#
#286
1#
b0000000000010000 )
#287
0#
#288
1#
b0000000000001111 )
#289
0#
#290
1#
b0000000000001110 )
#291
0#
#292
1#
b0000000000001101 )
#293
0#
#294
1#
b0000000000001100 )
#295
0#
#296
1#
b0000000000001011 )
#297
0#
#298
1#
b0000000000001010 )
#299
0#
#300
1#
b0000000000001001 )
#301
0#
#302
1#
b0000000000001000 )
#303
0#
#304
1#
b0000000000000111 )
#305
0#
#306
1#
b0000000000000110 )
#307
0#
#308
1#
b0000000000000101 )
#309
0#
#310
1#
b0000000000000100 )
#311
0#
#312
1#
b0000000000000011 )
#313
0#
#314
1#
b0000000000000010 )
#315
0#
#316
1#
b0000000000000001 )
#317
0#
#318
1#
b0000000000000000 )
#319
0#
#320
1#
1'
b00111111 (
b0000000000011001 )
b00000000000000000000000000000110 *
b00000000000000000000000000000111 +
#321
0#
#322
1#
0'
b0000000000011000 )
#323
0#
#324
1#
b0000000000010111 )
#325
0#
#326
1#
b0000000000010110 )
#327
0#
#328
1#
b0000000000010101 )
#329
0#
#330
1#
b0000000000010100 )
#331
0#
#332
1#
b0000000000010011 )
#333
0#
#334
1#
b0000000000010010 )
#335
0#
#336
1#
b0000000000010001 )
#337
0#
#338
1#
b0000000000010000 )
#339
0#
#340
1#
b0000000000001111 )
#341
0#
#342
1#
b0000000000001110 )
#343
0#
#344
1#
b0000000000001101 )
#345
0#
#346
1#
b0000000000001100 )
#347
0#
#348
1#
b0000000000001011 )
#349
0#
#350
1#
b0000000000001010 )
#351
0#
#352
1#
b0000000000001001 )
#353
0#
#354
1#
b0000000000001000 )
#355
0#
#356
1#
b0000000000000111 )
#357
0#
#358
1#
b0000000000000110 )
#359
0#
#360
1#
b0000000000000101 )
#361
0#
#362
1#
b0000000000000100 )
#363
0#
#364
1#
b0000000000000011 )
#365
0#
#366
1#
b0000000000000010 )
#367
0#
#368
1#
b0000000000000001 )
#369
0#
#370
1#
b0000000000000000 )
#371
0#
#372
1#
1'
b01111111 (
b0000000000011001 )
b00000000000000000000000000000111 *
b00000000000000000000000000001000 +
#373
0#
#374
1#
0'
b0000000000011000 )
#375
0#
#376
1#
b0000000000010111 )
#377
0#
#378
1#
b0000000000010110 )
#379
0#
#380
1#
b0000000000010101 )
#381
0#
#382
1#
b0000000000010100 )
#383
0#
#384
1#
b0000000000010011 )
#385
0#
#386
1#
b0000000000010010 )
#387
0#
#388
1#
b0000000000010001 )
#389
0#
#390
1#
b0000000000010000 )
#391
0#
#392
1#
b0000000000001111 )
#393
0#
#394
1#
b0000000000001110 )
#395
0#
#396
1#
b0000000000001101 )
#397
0#
#398
1#
b0000000000001100 )
#399
0#
#400
1#
b0000000000001011 )
#401
0#
#402
1#
b0000000000001010 )
#403
0#
#404
1#
b0000000000001001 )
#405
0#
#406
1#
b0000000000001000 )
#407
0#
#408
1#
b0000000000000111 )
#409
0#
#410
1#
b0000000000000110 )
#411
0#
#412
1#
b0000000000000101 )
#413
0#
#414
1#
b0000000000000100 )
#415
0#
#416
1#
b0000000000000011 )
#417
0#
#418
1#
b0000000000000010 )
#419
0#
#420
1#
b0000000000000001 )
#421
0#
#422
1#
b0000000000000000 )
#423
0#
#424
1#
1'
b11111111 (
b0000000000011001 )
b00000000000000000000000000001000 *
b00000000000000000000000000000000 +
#425
0#
#426
1#
0'
b0000000000011000 )
#427
0#
#428
1#
b0000000000010111 )
#429
0#
#430
1#
b0000000000010110 )
#431
0#
#432
1#
b0000000000010101 )
#433
0#
#434
1#
b0000000000010100 )
#435
0#
#436
1#
b0000000000010011 )
#437
0#
#438
1#
b0000000000010010 )
#439
0#
#440
1#
b0000000000010001 )
#441
0#
#442
1#
b0000000000010000 )
#443
0#
#444
1#
b0000000000001111 )
#445
0#
#446
1#
b0000000000001110 )
#447
0#
#448
1#
b0000000000001101 )
#449
0#
#450
1#
b0000000000001100 )
#451
0#
#452
1#
b0000000000001011 )
#453
0#
#454
1#
b0000000000001010 )
#455
0#
#456
1#
b0000000000001001 )
#457
0#
#458
1#
b0000000000001000 )
#459
0#
#460
1#
b0000000000000111 )
#461
0#
#462
1#
b0000000000000110 )
#463
0#
#464
1#
b0000000000000101 )
#465
0#
#466
1#
b0000000000000100 )
#467
0#
#468
1#
b0000000000000011 )
#469
0#
#470
1#
b0000000000000010 )
#471
0#
#472
1#
b0000000000000001 )
#473
0#
#474
1#
b0000000000000000 )
#475
0#
#476
1#
1'
b00000000 (
b0000000000011001 )
b00000000000000000000000000000000 *
b00000000000000000000000000000001 +
#477
0#
#478
1#
0'
b0000000000011000 )
#479
0#
#480
1#
b0000000000010111 )
#481
0#
#482
1#
b0000000000010110 )
#483
0#
#484
1#
b0000000000010101 )
#485
0#
#486
1#
b0000000000010100 )
#487
0#
#488
1#
b0000000000010011 )
#489
0#
#490
1#
b0000000000010010 )
#491
0#
#492
1#
b0000000000010001 )
#493
0#
#494
1#
b0000000000010000 )
#495
0#
#496
1#
b0000000000001111 )
#497
0#
#498
1#
b0000000000001110 )
#499
0#
#500
1#
b0000000000001101 )
#501
0#
#502
1#
b0000000000001100 )
#503
0#
#504
1#
b0000000000001011 )
#505
0#
#506
1#
b0000000000001010 )
#507
0#
#508
1#
b0000000000001001 )
#509
0#
#510
1#
b0000000000001000 )
#511
0#
#512
1#
b0000000000000111 )
#513
0#
#514
1#
b0000000000000110 )
#515
0#
#516
1#
b0000000000000101 )
#517
0#
#518
1#
b0000000000000100 )
#519
0#
#520
1#
b0000000000000011 )
#521
0#
#522
1#
b0000000000000010 )
#523
0#
#524
1#
b0000000000000001 )
#525
0#
#526
1#
b0000000000000000 )
#527
0#
#528
1#
1'
b00000001 (
b0000000000011001 )
b00000000000000000000000000000001 *
b00000000000000000000000000000010 +
#529
0#
#530
1#
0'
b0000000000011000 )
#531
0#
#532
1#
b0000000000010111 )
#533
0#
#534
1#
b0000000000010110 )
#535
0#
#536
1#
b0000000000010101 )
#537
0#
#538
1#
b0000000000010100 )
#539
0#
#540
1#
b0000000000010011 )
#541
0#
#542
1#
b0000000000010010 )
#543
0#
#544
1#
b0000000000010001 )
#545
0#
#546
1#
b0000000000010000 )
#547
0#
#548
1#
b0000000000001111 )
#549
0#
#550
1#
b0000000000001110 )
#551
0#
#552
1#
b0000000000001101 )
#553
0#
#554
1#
b0000000000001100 )
#555
0#
#556
1#
b0000000000001011 )
#557
0#
#558
1#
b0000000000001010 )
#559
0#
#560
1#
b0000000000001001 )
#561
0#
#562
1#
b0000000000001000 )
#563
0#
#564
1#
b0000000000000111 )
#565
0#
#566
1#
b0000000000000110 )
#567
0#
#568
1#
b0000000000000101 )
#569
0#
#570
1#
b0000000000000100 )
#571
0#
#572
1#
b0000000000000011 )
#573
0#
#574
1#
b0000000000000010 )
#575
0#
#576
1#
b0000000000000001 )
#577
0#
#578
1#
b0000000000000000 )
#579
0#
#580
1#
1'
b00000011 (
b0000000000011001 )
b00000000000000000000000000000010 *
b00000000000000000000000000000011 +
#581
0#
#582
1#
0'
b0000000000011000 )
#583
0#
#584
1#
b0000000000010111 )
#585
0#
#586
1#
b0000000000010110 )
#587
0#
#588
1#
b0000000000010101 )
#589
0#
#590
1#
b0000000000010100 )
#591
0#
#592
1#
b0000000000010011 )
#593
0#
#594
1#
b0000000000010010 )
#595
0#
#596
1#
b0000000000010001 )
#597
0#
#598
1#
b0000000000010000 )
#599
0#
#600
1#
b0000000000001111 )
#601
0#
#602
1#
b0000000000001110 )
#603
0#
#604
1#
b0000000000001101 )
#605
0#
#606
1#
b0000000000001100 )
#607
0#
#608
1#
b0000000000001011 )
#609
0#
#610
1#
b0000000000001010 )
#611
0#
#612
1#
b0000000000001001 )
#613
0#
#614
1#
b0000000000001000 )
#615
0#
#616
1#
b0000000000000111 )
#617
0#
#618
1#
b0000000000000110 )
#619
0#
#620
1#
b0000000000000101 )
#621
0#
#622
1#
b0000000000000100 )
#623
0#
#624
1#
b0000000000000011 )
#625
0#
#626
1#
b0000000000000010 )
#627
0#
#628
1#
b0000000000000001 )
#629
0#
#630
1#
b0000000000000000 )
#631
0#
#632
1#
1'
b00000111 (
b0000000000011001 )
b00000000000000000000000000000011 *
b00000000000000000000000000000100 +
#633
0#
#634
1#
0'
b0000000000011000 )
#635
0#
#636
1#
b0000000000010111 )
#637
0#
#638
1#
b0000000000010110 )
#639
0#
#640
1#
b0000000000010101 )
#641
0#
#642
1#
b0000000000010100 )
#643
0#
#644
1#
b0000000000010011 )
#645
0#
#646
1#
b0000000000010010 )
#647
0#
#648
1#
b0000000000010001 )
#649
0#
#650
1#
b0000000000010000 )
#651
0#
#652
1#
b0000000000001111 )
#653
0#
#654
1#
b0000000000001110 )
#655
0#
#656
1#
b0000000000001101 )
#657
0#
#658
1#
b0000000000001100 )
#659
0#
#660
1#
b0000000000001011 )
#661
0#
#662
1#
b0000000000001010 )
#663
0#
#664
1#
b0000000000001001 )
#665
0#
#666
1#
b0000000000001000 )
#667
0#
#668
1#
b0000000000000111 )
#669
0#
#670
1#
b0000000000000110 )
#671
0#
#672
1#
b0000000000000101 )
#673
0#
#674
1#
b0000000000000100 )
#675
0#
#676
1#
b0000000000000011 )
#677
0#
#678
1#
b0000000000000010 )
#679
0#
#680
1#
b0000000000000001 )
#681
0#
#682
1#
b0000000000000000 )
#683
0#
#684
1#
1'
b00001111 (
b0000000000011001 )
b00000000000000000000000000000100 *
b00000000000000000000000000000101 +
#685
0#
#686
1#
0'
b0000000000011000 )
#687
0#
#688
1#
b0000000000010111 )
#689
0#
#690
1#
b0000000000010110 )
#691
0#
#692
1#
b0000000000010101 )
#693
0#
#694
1#
b0000000000010100 )
#695
0#
#696
1#
b0000000000010011 )
#697
0#
#698
1#
b0000000000010010 )
#699
0#
#700
1#
b0000000000010001 )
#701
0#
#702
1#
b0000000000010000 )
#703
0#
#704
1#
b0000000000001111 )
#705
0#
#706
1#
b0000000000001110 )
#707
0#
#708
1#
b0000000000001101 )
#709
0#
#710
1#
b0000000000001100 )
#711
0#
#712
1#
b0000000000001011 )
#713
0#
#714
1#
b0000000000001010 )
#715
0#
#716
1#
b0000000000001001 )
#717
0#
#718
1#
b0000000000001000 )
#719
0#
#720
1#
b0000000000000111 )
#721
0#
#722
1#
b0000000000000110 )
#723
0#
#724
1#
b0000000000000101 )
#725
0#
#726
1#
b0000000000000100 )
#727
0#
#728
1#
b0000000000000011 )
#729
0#
#730
1#
b0000000000000010 )
#731
0#
#732
1#
b0000000000000001 )
#733
0#
#734
1#
b0000000000000000 )
#735
0#
#736
1#
1'
b00011111 (
b0000000000011001 )
b00000000000000000000000000000101 *
b00000000000000000000000000000110 +
#737
0#
#738
1#
0'
b0000000000011000 )
#739
0#
#740
1#
b0000000000010111 )
#741
0#
#742
1#
b0000000000010110 )
#743
0#
#744
1#
b0000000000010101 )
#745
0#
#746
1#
b0000000000010100 )
#747
0#
#748
1#
b0000000000010011 )
#749
0#
#750
1#
b0000000000010010 )
#751
0#
#752
1#
b0000000000010001 )
#753
0#
#754
1#
b0000000000010000 )
#755
0#
#756
1#
b0000000000001111 )
#757
0#
#758
1#
b0000000000001110 )
#759
0#
#760
1#
b0000000000001101 )
#761
0#
#762
1#
b0000000000001100 )
#763
0#
#764
1#
b0000000000001011 )
#765
0#
#766
1#
b0000000000001010 )
#767
0#
#768
1#
b0000000000001001 )
#769
0#
#770
1#
b0000000000001000 )
#771
0#
#772
1#
b0000000000000111 )
#773
0#
#774
1#
b0000000000000110 )
#775
0#
#776
1#
b0000000000000101 )
#777
0#
#778
1#
b0000000000000100 )
#779
0#
#780
1#
b0000000000000011 )
#781
0#
#782
1#
b0000000000000010 )
#783
0#
#784
1#
b0000000000000001 )
#785
0#
#786
1#
b0000000000000000 )
#787
0#
#788
1#
1'
b00111111 (
b0000000000011001 )
b00000000000000000000000000000110 *
b00000000000000000000000000000111 +
#789
0#
#790
1#
0'
b0000000000011000 )
#791
0#
#792
1#
b0000000000010111 )
#793
0#
#794
1#
b0000000000010110 )
#795
0#
#796
1#
b0000000000010101 )
#797
0#
#798
1#
b0000000000010100 )
#799
0#
#800
1#
b0000000000010011 )
#801
0#
#802
1#
b0000000000010010 )
#803
0#
#804
1#
b0000000000010001 )
#805
0#
#806
1#
b0000000000010000 )
#807
0#
#808
1#
b0000000000001111 )
#809
0#
#810
1#
b0000000000001110 )
#811
0#
#812
1#
b0000000000001101 )
#813
0#
#814
1#
b0000000000001100 )
#815
0#
#816
1#
b0000000000001011 )
#817
0#
#818
1#
b0000000000001010 )
#819
0#
#820
1#
b0000000000001001 )
#821
0#
#822
1#
b0000000000001000 )
#823
0#
#824
1#
b0000000000000111 )
#825
0#
#826
1#
b0000000000000110 )
#827
0#
#828
1#
b0000000000000101 )
#829
0#
#830
1#
b0000000000000100 )
#831
0#
#832
1#
b0000000000000011 )
#833
0#
#834
1#
b0000000000000010 )
#835
0#
#836
1#
b0000000000000001 )
#837
0#
#838
1#
b0000000000000000 )
#839
0#
#840
1#
1'
b01111111 (
b0000000000011001 )
b00000000000000000000000000000111 *
b00000000000000000000000000001000 +
#841
0#
#842
1#
0'
b0000000000011000 )
#843
0#
#844
1#
b0000000000010111 )
#845
0#
#846
1#
b0000000000010110 )
#847
0#
#848
1#
b0000000000010101 )
#849
0#
#850
1#
b0000000000010100 )
#851
0#
#852
1#
b0000000000010011 )
#853
0#
#854
1#
b0000000000010010 )
#855
0#
#856
1#
b0000000000010001 )
#857
0#
#858
1#
b0000000000010000 )
#859
0#
#860
1#
b0000000000001111 )
#861
0#
#862
1#
b0000000000001110 )
#863
0#
#864
1#
b0000000000001101 )
#865
0#
#866
1#
b0000000000001100 )
#867
0#
#868
1#
b0000000000001011 )
#869
0#
#870
1#
b0000000000001010 )
#871
0#
#872
1#
b0000000000001001 )
#873
0#
#874
1#
b0000000000001000 )
#875
0#
#876
1#
b0000000000000111 )
#877
0#
#878
1#
b0000000000000110 )
#879
0#
#880
1#
b0000000000000101 )
#881
0#
#882
1#
b0000000000000100 )
#883
0#
#884
1#
b0000000000000011 )
#885
0#
#886
1#
b0000000000000010 )
#887
0#
#888
1#
b0000000000000001 )
#889
0#
#890
1#
b0000000000000000 )
#891
0#
#892
1#
1'
b11111111 (
b0000000000011001 )
b00000000000000000000000000001000 *
b00000000000000000000000000000000 +
#893
0#
#894
1#
0'
b0000000000011000 )
#895
0#
#896
1#
b0000000000010111 )
#897
0#
#898
1#
b0000000000010110 )
#899
0#
#900
1#
b0000000000010101 )
#901
0#
#902
1#
b0000000000010100 )
#903
0#
#904
1#
b0000000000010011 )
#905
0#
#906
1#
b0000000000010010 )
#907
0#
#908
1#
b0000000000010001 )
#909
0#
#910
1#
b0000000000010000 )
#911
0#
#912
1#
b0000000000001111 )
#913
0#
#914
1#
b0000000000001110 )
#915
0#
#916
1#
b0000000000001101 )
#917
0#
#918
1#
b0000000000001100 )
#919
0#
#920
1#
b0000000000001011 )
#921
0#
#922
1#
b0000000000001010 )
#923
0#
#924
1#
b0000000000001001 )
#925
0#
#926
1#
b0000000000001000 )
#927
0#
#928
1#
b0000000000000111 )
#929
0#
#930
1#
b0000000000000110 )
#931
0#
#932
1#
b0000000000000101 )
#933
0#
#934
1#
b0000000000000100 )
#935
0#
#936
1#
b0000000000000011 )
#937
0#
#938
1#
b0000000000000010 )
#939
0#
#940
1#
b0000000000000001 )
#941
0#
#942
1#
b0000000000000000 )
#943
0#
#944
1#
1'
b00000000 (
b0000000000011001 )
b00000000000000000000000000000000 *
b00000000000000000000000000000001 +
#945
0#
#946
1#
0'
b0000000000011000 )
#947
0#
#948
1#
b0000000000010111 )
#949
0#
#950
1#
b0000000000010110 )
#951
0#
#952
1#
b0000000000010101 )
#953
0#
#954
1#
b0000000000010100 )
#955
0#
#956
1#
b0000000000010011 )
#957
0#
#958
1#
b0000000000010010 )
#959
0#
#960
1#
b0000000000010001 )
#961
0#
#962
1#
b0000000000010000 )
#963
0#
#964
1#
b0000000000001111 )
#965
0#
#966
1#
b0000000000001110 )
#967
0#
#968
1#
b0000000000001101 )
#969
0#
#970
1#
b0000000000001100 )
#971
0#
#972
1#
b0000000000001011 )
#973
0#
#974
1#
b0000000000001010 )
#975
0#
#976
1#
b0000000000001001 )
#977
0#
#978
1#
b0000000000001000 )
#979
0#
#980
1#
b0000000000000111 )
#981
0#
#982
1#
b0000000000000110 )
#983
0#
#984
1#
b0000000000000101 )
#985
0#
#986
1#
b0000000000000100 )
#987
0#
#988
1#
b0000000000000011 )
#989
0#
#990
1#
b0000000000000010 )
#991
0#
#992
1#
b0000000000000001 )
#993
0#
#994
1#
b0000000000000000 )
#995
0#
#996
1#
1'
b00000001 (
b0000000000011001 )
b00000000000000000000000000000001 *
b00000000000000000000000000000010 +
#997
0#
#998
1#
0'
b0000000000011000 )
#999
0#
#1000
1#
b0000000000010111 )
#1001
0#
#1002
1#
b0000000000010110 )
#1003
0#
#1004
1#
b0000000000010101 )
#1005
0#
#1006
1#
b0000000000010100 )
#1007
0#
#1008
1#
b0000000000010011 )
#1009
0#
#1010
1#
b0000000000010010 )
#1011
0#
#1012
1#
b0000000000010001 )
#1013
0#
#1014
1#
b0000000000010000 )
#1015
0#
#1016
1#
b0000000000001111 )
#1017
0#
#1018
1#
b0000000000001110 )
#1019
0#
#1020
1#
b0000000000001101 )
#1021
0#
#1022
1#
b0000000000001100 )
#1023
0#
#1024
1#
b0000000000001011 )
#1025
0#
#1026
1#
b0000000000001010 )
#1027
0#
#1028
1#
b0000000000001001 )
#1029
0#
#1030
1#
b0000000000001000 )
#1031
0#
#1032
1#
b0000000000000111 )
#1033
0#
#1034
1#
b0000000000000110 )
#1035
0#
#1036
1#
b0000000000000101 )
#1037
0#
#1038
1#
b0000000000000100 )
#1039
0#
#1040
1#
b0000000000000011 )
#1041
0#
#1042
1#
b0000000000000010 )
#1043
0#
#1044
1#
b0000000000000001 )
#1045
0#
#1046
1#
b0000000000000000 )
#1047
0#
#1048
1#
1'
b00000011 (
b0000000000011001 )
b00000000000000000000000000000010 *
b00000000000000000000000000000011 +
#1049
0#
#1050
1#
0'
b0000000000011000 )
#1051
0#
#1052
1#
b0000000000010111 )
#1053
0#
#1054
1#
b0000000000010110 )
#1055
0#
#1056
1#
b0000000000010101 )
#1057
0#
#1058
1#
b0000000000010100 )
#1059
0#
#1060
1#
b0000000000010011 )
#1061
0#
#1062
1#
b0000000000010010 )
#1063
0#
#1064
1#
b0000000000010001 )
#1065
0#
#1066
1#
b0000000000010000 )
#1067
0#
#1068
1#
b0000000000001111 )
#1069
0#
#1070
1#
b0000000000001110 )
#1071
0#
#1072
1#
b0000000000001101 )
#1073
0#
#1074
1#
b0000000000001100 )
#1075
0#
#1076
1#
b0000000000001011 )
#1077
0#
#1078
1#
b0000000000001010 )
#1079
0#
#1080
1#
b0000000000001001 )
#1081
0#
#1082
1#
b0000000000001000 )
#1083
0#
#1084
1#
b0000000000000111 )
#1085
0#
#1086
1#
b0000000000000110 )
#1087
0#
#1088
1#
b0000000000000101 )
#1089
0#
#1090
1#
b0000000000000100 )
#1091
0#
#1092
1#
b0000000000000011 )
#1093
0#
#1094
1#
b0000000000000010 )
#1095
0#
#1096
1#
b0000000000000001 )
#1097
0#
#1098
1#
b0000000000000000 )
#1099
0#
#1100
1#
1'
b00000111 (
b0000000000011001 )
b00000000000000000000000000000011 *
b00000000000000000000000000000100 +
#1101
0#
#1102
1#
0'
b0000000000011000 )
#1103
0#
#1104
1#
b0000000000010111 )
#1105
0#
#1106
1#
b0000000000010110 )
#1107
0#
#1108
1#
b0000000000010101 )
#1109
0#
#1110
1#
b0000000000010100 )
#1111
0#
#1112
1#
b0000000000010011 )
#1113
0#
#1114
1#
b0000000000010010 )
#1115
0#
#1116
1#
b0000000000010001 )
#1117
0#
#1118
1#
b0000000000010000 )
#1119
0#
#1120
1#
b0000000000001111 )
#1121
0#
#1122
1#
b0000000000001110 )
